{
  "dashboard": {
    "title": "Algo Trading Bot - Trading Metrics",
    "description": "Real-time trading performance monitoring",
    "tags": [
      "trading",
      "performance"
    ],
    "timezone": "browser",
    "panels": [
      {
        "title": "Win Rate",
        "type": "stat",
        "gridPos": {
          "x": 0,
          "y": 0,
          "w": 6,
          "h": 4
        },
        "targets": [
          {
            "expr": "trading_win_rate",
            "legendFormat": "Win Rate"
          }
        ],
        "fieldConfig": {
          "defaults": {
            "unit": "percentunit",
            "custom": {
              "hideFrom": {
                "tooltip": false,
                "viz": false,
                "legend": false
              }
            },
            "color": {
              "mode": "thresholds"
            },
            "thresholds": {
              "mode": "percentage",
              "steps": [
                {
                  "color": "red",
                  "value": 0
                },
                {
                  "color": "yellow",
                  "value": 40
                },
                {
                  "color": "green",
                  "value": 50
                }
              ]
            }
          }
        }
      },
      {
        "title": "Total P&L",
        "type": "stat",
        "gridPos": {
          "x": 6,
          "y": 0,
          "w": 6,
          "h": 4
        },
        "targets": [
          {
            "expr": "trading_total_pnl",
            "legendFormat": "P&L"
          }
        ],
        "fieldConfig": {
          "defaults": {
            "unit": "currencyUSD",
            "custom": {
              "hideFrom": {
                "tooltip": false,
                "viz": false,
                "legend": false
              }
            },
            "color": {
              "mode": "thresholds"
            },
            "thresholds": {
              "mode": "percentage",
              "steps": [
                {
                  "color": "red",
                  "value": -10000
                },
                {
                  "color": "yellow",
                  "value": 0
                },
                {
                  "color": "green",
                  "value": 10000
                }
              ]
            }
          }
        }
      },
      {
        "title": "Max Drawdown",
        "type": "stat",
        "gridPos": {
          "x": 12,
          "y": 0,
          "w": 6,
          "h": 4
        },
        "targets": [
          {
            "expr": "trading_max_drawdown",
            "legendFormat": "Max DD"
          }
        ],
        "fieldConfig": {
          "defaults": {
            "unit": "percentunit",
            "custom": {
              "hideFrom": {
                "tooltip": false,
                "viz": false,
                "legend": false
              }
            },
            "color": {
              "mode": "thresholds"
            },
            "thresholds": {
              "mode": "percentage",
              "steps": [
                {
                  "color": "green",
                  "value": 0
                },
                {
                  "color": "yellow",
                  "value": 15
                },
                {
                  "color": "red",
                  "value": 25
                }
              ]
            }
          }
        }
      },
      {
        "title": "Trade Count",
        "type": "stat",
        "gridPos": {
          "x": 18,
          "y": 0,
          "w": 6,
          "h": 4
        },
        "targets": [
          {
            "expr": "trading_total_trades",
            "legendFormat": "Trades"
          }
        ],
        "fieldConfig": {
          "defaults": {
            "unit": "short",
            "color": {
              "mode": "value"
            }
          }
        }
      },
      {
        "title": "Portfolio Value Over Time",
        "type": "timeseries",
        "gridPos": {
          "x": 0,
          "y": 4,
          "w": 12,
          "h": 8
        },
        "targets": [
          {
            "expr": "trading_portfolio_value",
            "legendFormat": "Portfolio Value"
          }
        ],
        "fieldConfig": {
          "defaults": {
            "unit": "currencyUSD",
            "custom": {
              "lineWidth": 2
            }
          }
        }
      },
      {
        "title": "Equity Curve (Cumulative Returns)",
        "type": "timeseries",
        "gridPos": {
          "x": 12,
          "y": 4,
          "w": 12,
          "h": 8
        },
        "targets": [
          {
            "expr": "trading_cumulative_return",
            "legendFormat": "Return %"
          }
        ],
        "fieldConfig": {
          "defaults": {
            "unit": "percentunit",
            "custom": {
              "lineWidth": 2
            }
          }
        }
      },
      {
        "title": "Daily P&L Distribution",
        "type": "histogram",
        "gridPos": {
          "x": 0,
          "y": 12,
          "w": 12,
          "h": 6
        },
        "targets": [
          {
            "expr": "histogram_quantile(0.95, trading_daily_pnl)",
            "legendFormat": "P&L Distribution"
          }
        ]
      },
      {
        "title": "Slippage Analysis",
        "type": "timeseries",
        "gridPos": {
          "x": 12,
          "y": 12,
          "w": 12,
          "h": 6
        },
        "targets": [
          {
            "expr": "trading_avg_slippage_bps",
            "legendFormat": "Avg Slippage (bps)"
          }
        ],
        "fieldConfig": {
          "defaults": {
            "unit": "short",
            "custom": {
              "lineWidth": 1
            }
          }
        }
      }
    ]
  }
}